README.md
setup.py
pyvg/__init__.py
pyvg/alignment.py
pyvg/alignmentcollection.py
pyvg/construct.py
pyvg/conversion.py
pyvg/graphstats.py
pyvg/sequences.py
pyvg/util.py
pyvg/vg_pb2.py
pyvg/vgobjects.py
pyvg/view.py
pyvg.egg-info/PKG-INFO
pyvg.egg-info/SOURCES.txt
pyvg.egg-info/dependency_links.txt
pyvg.egg-info/not-zip-safe
pyvg.egg-info/requires.txt
pyvg.egg-info/top_level.txt