Metadata-Version: 1.1
Name: pyvg
Version: 1.1.3
Summary: Working with vg graphs in python
Home-page: http://github.com/uio-bmi/pyvg
Author: Ivar Grytten and Knut Rand
Author-email: UNKNOWN
License: MIT
Platform: UNKNOWN
Classifier: Programming Language :: Python :: 3
